google_api_service_helper/__init__.py
google_api_service_helper/drive/__init__.py
google_api_service_helper/drive/schemas.py
google_api_service_helper/drive/service.py
google_api_service_helper/sheets/__init__.py
google_api_service_helper/sheets/schemas.py
google_api_service_helper/sheets/service.py
google_api_service_helper/utils.py
google_api_service_helper-0.1.1.dist-info/METADATA
google_api_service_helper-0.1.1.dist-info/WHEEL
google_api_service_helper-0.1.1.dist-info/RECORD
